{"components_base_card.md":"CayE6znF","components_base_copy-text.md":"C87lZqei","components_base_editor.md":"DB9fY0s_","components_base_icon.md":"Dy4jhuPq","components_base_image.md":"IBKkEwq6","components_base_line.md":"D_y-vH_C","components_base_loading.md":"bSwwdx_n","components_base_menu.md":"BVf57w8v","components_base_noticebar.md":"CcQBG7Gu","components_base_pagination.md":"BHe6YbcQ","components_base_text-fold.md":"DFlBZabk","components_generate_epadaptpage.md":"BeZhDxW2","components_generate_epadminlayout.md":"WmldKjNG","components_generate_epauthpage.md":"VtrFR9ET","components_generate_epbuttons.md":"B-nPODu9","components_generate_epcard.md":"SkT_I-Jc","components_generate_epcomment.md":"DL0PENjY","components_generate_epcommentlayout.md":"ClRF3uma","components_generate_epcopytext.md":"Ueiey-hk","components_generate_epdialog.md":"OYGNhqtV","components_generate_epdiamondloading.md":"Brl5Ttmu","components_generate_epeditor.md":"DVV_ZfS8","components_generate_epformitem.md":"CLAWDvia","components_generate_epformschema.md":"BMPlHc0B","components_generate_epicon.md":"B-JGfna_","components_generate_epimage.md":"ecBUSTmi","components_generate_epletterloading.md":"CM49MEpR","components_generate_epline.md":"BZwVQBsN","components_generate_epmenu.md":"CDJURNMb","components_generate_epmenuitem.md":"DtKKg9UY","components_generate_epnoticebar.md":"CBaq5UEM","components_generate_eppagination.md":"C_qNJr71","components_generate_epskeleton.md":"BBqch2zv","components_generate_epslideloading.md":"Bd8u6CKy","components_generate_eptable.md":"BpkWV8jO","components_generate_eptablecolumn.md":"CGJzOk_B","components_generate_eptextfold.md":"DbFw-dYf","components_generate_epvirtuallist.md":"B0h5N7Dh","components_generate_index.md":"D-grWCAd","components_hooks_action-message.md":"D_XZBLRB","components_senior_adapt-page.md":"C_safwZT","components_senior_admin-layout.md":"pCaXdWgf","components_senior_comment.md":"BAUXEhLY","components_senior_dialog.md":"BlRydlVX","components_senior_form-schema.md":"DjJTRAH8","components_senior_table.md":"DOWmcYib","components_senior_virtual-list.md":"CCR4pkJm","components_template_auth-page.md":"BN88FU0V","components_type_card.md":"OyC9WC1M","components_type_comment.md":"D8pp1TTy","components_type_editor.md":"CJuyksFn","components_type_form-schema.md":"V9X9Z0pX","components_type_form.md":"DfgOJ32b","components_type_icon.md":"Bny0K7Yr","components_type_image.md":"73e7R0jZ","components_type_line.md":"CNzSmLVW","components_type_loading.md":"CNlLxc24","components_type_menu.md":"Ce6l6BZU","components_type_notice-bar.md":"D59qZW9q","components_type_pagination.md":"akHXnIsr","components_type_table.md":"DCBLW1au","components_type_text-fold.md":"DNDRj_o-","components_type_virtual-list.md":"p_we4FLL","guide_changelog.md":"CemYit3J","guide_install.md":"DctAL1jw","index.md":"DRL2wO3z"}
